syutils/__init__.py
syutils/syutils.py
syutils-0.0.7.dist-info/LICENSE
syutils-0.0.7.dist-info/METADATA
syutils-0.0.7.dist-info/WHEEL
syutils-0.0.7.dist-info/top_level.txt
syutils-0.0.7.dist-info/RECORD
