Metadata-Version: 2.1
Name: syutils
Version: 0.0.7
Summary: High frequency functions and class
Home-page: https://gitee.com/wdy0401/syutils
Author: wangdeyang
Author-email: wdy0401@gmail.com
License: MIT
License-File: LICENSE
Requires-Dist: trade-date
Requires-Dist: py7zr
